<?xml version=”1.0″?><slides>	<slide>
		<pic>Ch5-Slides.001.png</pic>
		<snd>slide1.mp3</snd>		
	</slide>
	<slide>
		<pic>Ch5-Slides.002.png</pic>
		<snd>slide2.mp3</snd>		
	</slide>
	<slide>
		<pic>Ch5-Slides.003.png</pic>
		<snd>slide3.mp3</snd>		
	</slide>
	<slide>
		<pic>Ch5-Slides.004.png</pic>
		<snd>slide4.mp3</snd>		
	</slide>
	<slide>
		<pic>Ch5-Slides.005.png</pic>
		<snd>slide5.mp3</snd>		
	</slide>
	<slide>
		<pic>Ch5-Slides.006.png</pic>
		<snd>slide6.mp3</snd>		
	</slide>
	<slide>
		<pic>Ch5-Slides.007.png</pic>
		<snd>slide7.mp3</snd>		
	</slide>
	<slide>
		<pic>Ch5-Slides.008.png</pic>
		<snd>slide8.mp3</snd>		
	</slide>
	<slide>
		<pic>Ch5-Slides.009.png</pic>
		<snd>slide9.mp3</snd>		
	</slide>
	<slide>
		<pic>Ch5-Slides.010.png</pic>
		<snd>slide10.mp3</snd>		
	</slide>
	<slide>
		<pic>Ch5-Slides.011.png</pic>
		<snd>slide11.mp3</snd>		
	</slide>

	<slide>
		<pic>Ch5-Slides.012.png</pic>
		<snd>slide12.mp3</snd>		
	</slide>

	<slide>
		<pic>Ch5-Slides.013.png</pic>
		<snd>slide12.mp3</snd>		
	</slide>

	<slide>
		<pic>Ch5-Slides.014.png</pic>
		<snd>slide12.mp3</snd>		
	</slide>

	<slide>
		<pic>Ch5-Slides.015.png</pic>
		<snd>slide12.mp3</snd>		
	</slide>

	<slide>
		<pic>Ch5-Slides.016.png</pic>
		<snd>slide16.mp3</snd>		
	</slide>

	<slide>
		<pic>Ch5-Slides.017.png</pic>
		<snd>slide17.mp3</snd>		
	</slide>

	<slide>
		<pic>Ch5-Slides.018.png</pic>
		<snd>slide18.mp3</snd>		
	</slide>

	<slide>
		<pic>Ch5-Slides.019.png</pic>
		<snd>slide19.mp3</snd>		
	</slide>
	<slide>
		<pic>Ch5-Slides.020.png</pic>
		<snd>slide20.mp3</snd>		
	</slide>
    
	<slide>
		<pic>Ch5-Slides.021.png</pic>
		<snd>slide21.mp3</snd>		
	</slide>

	<slide>
		<pic>Ch5-Slides.022.png</pic>
		<snd>slide22.mp3</snd>		
	</slide>
	<slide>
		<pic>Ch5-Slides.023.png</pic>
		<snd>slide23.mp3</snd>		
	</slide>
	<slide>
		<pic>Ch5-Slides.024.png</pic>
		<snd>slide24.mp3</snd>		
	</slide>


</slides>